smoothDE/__init__.py
smoothDE/estimator.py
smoothDE/estimator_predictor.py
smoothDE/find_tf.py
smoothDE/integrate_dphidt.py
smoothDE/interpolator_transformer.py
smoothDE/make_subfields.py
smoothDE/maxent.py
smoothDE/maxent_optimization_fun.py
smoothDE/optimize_phi.py
smoothde-1.4.1.dist-info/LICENSE
smoothde-1.4.1.dist-info/METADATA
smoothde-1.4.1.dist-info/WHEEL
smoothde-1.4.1.dist-info/top_level.txt
smoothde-1.4.1.dist-info/RECORD
